[{"target": "Db", "source": "Fm7b5", "value": 5}, {"target": "E/5", "source": "Gb9", "value": 8}, {"value": 8, "source": "Bb", "target": "Fm"}, {"target": "B", "value": 10, "source": "Gm"}, {"target": "Eb/3", "value": 8, "source": "B"}, {"target": "Eb/5", "source": "Dbm", "value": 10}, {"source": "Em7b5", "target": "A", "value": 5}, {"source": "Eb", "value": 20, "target": "E"}, {"source": "G", "value": 10, "target": "Am"}, {"value": 8, "target": "Gb/5", "source": "E9"}, {"source": "Fm", "value": 10, "target": "C/5"}, {"target": "A", "value": 5, "source": "Ebm7b5"}, {"target": "Abm", "value": 10, "source": "B"}, {"source": "Db", "target": "D", "value": 20}, {"value": 5, "target": "Gb", "source": "Abm6"}, {"source": "Bm7", "target": "Gb", "value": 8}, {"value": 8, "target": "G", "source": "Db7"}, {"target": "A", "value": 20, "source": "E"}, {"value": 20, "source": "Bb", "target": "Gb"}, {"source": "Dbm7b5", "target": "Gb", "value": 5}, {"source": "F", "target": "Fm", "value": 10}, {"value": 5, "target": "Am", "source": "Adim7"}, {"target": "Db", "value": 10, "source": "Bbm"}, {"source": "Am", "target": "Eb", "value": 8}, {"source": "F", "target": "Gbm", "value": 10}, {"source": "Ddim7", "target": "Bbm", "value": 5}, {"source": "E", "value": 10, "target": "Ebm"}, {"value": 8, "target": "G", "source": "Ab"}, {"value": 8, "source": "Bb", "target": "G"}, {"source": "Abdim7", "target": "Gbm", "value": 5}, {"target": "Em", "value": 5, "source": "Adim7"}, {"target": "A", "source": "Dbm", "value": 8}, {"value": 10, "target": "Bb", "source": "B"}, {"source": "C", "value": 10, "target": "Cm"}, {"source": "F", "value": 15, "target": "Bb"}, {"source": "Cm", "value": 10, "target": "C/5"}, {"target": "D", "value": 5, "source": "Gbm6"}, {"source": "F", "target": "D", "value": 10}, {"source": "Ab7", "value": 8, "target": "C/5"}, {"target": "Abm", "source": "Cm", "value": 10}, {"source": "Cm7b5", "value": 5, "target": "Ab"}, {"target": "F", "value": 5, "source": "Am7b5"}, {"source": "B/3", "value": 8, "target": "Fm"}, {"source": "Bb", "value": 10, "target": "Cm"}, {"value": 10, "target": "Ebm", "source": "B"}, {"value": 8, "source": "C/3", "target": "Dm"}, {"source": "Db", "value": 15, "target": "C"}, {"target": "Abm", "value": 8, "source": "D/3"}, {"source": "Ddim7", "value": 5, "target": "Am"}, {"source": "Fm", "target": "Dm", "value": 10}, {"source": "C", "target": "Eb/3", "value": 8}, {"value": 5, "target": "Am", "source": "Fdim7"}, {"value": 8, "source": "D", "target": "Bb"}, {"source": "Eb", "target": "B", "value": 8}, {"target": "Db", "source": "Bm", "value": 10}, {"target": "A", "value": 5, "source": "Am7b5"}, {"source": "F", "target": "A", "value": 12}, {"source": "Db", "target": "Gbm", "value": 10}, {"target": "B", "value": 5, "source": "Gbm7b5"}, {"value": 10, "target": "C/5", "source": "Dm"}, {"target": "Bm", "value": 8, "source": "D"}, {"value": 8, "source": "Bb", "target": "Am"}, {"target": "D", "value": 5, "source": "Ebm7b5"}, {"source": "F", "value": 10, "target": "Bb"}, {"source": "Ebdim7", "value": 5, "target": "Cm"}, {"value": 8, "target": "Am", "source": "Ab"}, {"source": "F", "target": "Dm", "value": 10}, {"value": 10, "target": "C/5", "source": "Gm"}, {"source": "Bm7b5", "target": "G", "value": 5}, {"target": "Ab", "value": 20, "source": "E"}, {"value": 8, "target": "C/5", "source": "Gbm7b5"}, {"target": "Eb/5", "source": "Gbm", "value": 10}, {"target": "Em", "value": 10, "source": "Dm"}, {"source": "C", "target": "A/3", "value": 8}, {"value": 5, "source": "Fm7b5", "target": "Bb"}, {"source": "Db", "value": 8, "target": "Bbm"}, {"target": "Gb", "source": "Gm7b5", "value": 5}, {"target": "F", "source": "Bm", "value": 10}, {"source": "Ebm", "target": "Fm", "value": 10}, {"source": "Bm7", "target": "Eb", "value": 8}, {"source": "Ebm", "value": 10, "target": "C/5"}, {"target": "Gb", "source": "B", "value": 12}, {"source": "Db", "target": "B", "value": 10}, {"source": "G", "value": 10, "target": "Cm"}, {"source": "Gb", "value": 10, "target": "Am"}, {"value": 8, "source": "Gb9", "target": "Bb/5"}, {"value": 5, "target": "Fm", "source": "Bbdim7"}, {"value": 8, "source": "Dbm", "target": "Eb"}, {"source": "Dbm", "target": "Am", "value": 10}, {"value": 5, "source": "Ab", "target": "E"}, {"value": 10, "source": "Em", "target": "E"}, {"source": "Bb", "value": 10, "target": "Am"}, {"target": "D", "source": "Cm6", "value": 5}, {"source": "D7", "value": 8, "target": "Gb/5"}, {"target": "Dbm", "value": 8, "source": "Bb"}, {"source": "Dbm7b5", "target": "Eb", "value": 5}, {"source": "F", "value": 8, "target": "Bbm"}, {"target": "E/5", "value": 8, "source": "Gbm7b5"}, {"target": "Db", "source": "D", "value": 5}, {"value": 8, "target": "Am", "source": "B"}, {"value": 8, "source": "E", "target": "G"}, {"source": "Eb", "value": 20, "target": "G"}, {"value": 10, "source": "Ab", "target": "E"}, {"value": 5, "source": "Gm7b5", "target": "C"}, {"source": "F", "value": 8, "target": "Db"}, {"source": "F", "target": "Gb", "value": 12}, {"value": 8, "source": "E", "target": "C"}, {"source": "Bm", "target": "Ebm", "value": 10}, {"value": 10, "source": "Bm", "target": "E"}, {"target": "G", "value": 10, "source": "Dm"}, {"source": "Gb", "value": 20, "target": "G"}, {"value": 8, "source": "Bb7", "target": "D/5"}, {"value": 5, "source": "Ebm7b5", "target": "E"}, {"value": 10, "target": "Bb", "source": "Gb/5"}, {"source": "Gb", "target": "B", "value": 10}, {"source": "Gbm", "target": "Abm", "value": 10}, {"target": "B", "source": "Bb", "value": 20}, {"target": "F", "source": "Abm7b5", "value": 5}, {"target": "Dbm", "value": 8, "source": "E"}, {"target": "Db", "value": 10, "source": "Ab"}, {"source": "Dbm", "target": "Ebm", "value": 10}, {"source": "Eb", "target": "F", "value": 10}, {"target": "E", "value": 10, "source": "A"}, {"value": 8, "target": "C/3", "source": "A"}, {"source": "F", "target": "C", "value": 12}, {"target": "B", "source": "Dm7b5", "value": 5}, {"source": "Eb", "target": "B", "value": 10}, {"target": "E/5", "source": "C9", "value": 8}, {"target": "G", "source": "Dbm", "value": 10}, {"source": "Db", "value": 15, "target": "Gb"}, {"target": "Db", "value": 5, "source": "Am7b5"}, {"target": "D", "value": 10, "source": "Abm"}, {"target": "Ab", "source": "Bm7b5", "value": 5}, {"target": "F", "source": "Em", "value": 10}, {"target": "Dbm", "value": 8, "source": "Ab"}, {"source": "Db", "value": 10, "target": "Cm"}, {"value": 10, "target": "Am", "source": "A"}, {"value": 8, "target": "Db/5", "source": "Gbm7b5"}, {"value": 8, "source": "G7", "target": "C"}, {"target": "Gm", "value": 10, "source": "Gm"}, {"value": 10, "target": "Ebm", "source": "A"}, {"source": "Eb", "target": "A/3", "value": 8}, {"value": 8, "source": "Ab", "target": "E"}, {"source": "Am", "target": "Dm", "value": 10}, {"target": "Eb/5", "source": "Em", "value": 10}, {"source": "F", "target": "G", "value": 10}, {"value": 8, "target": "Dm", "source": "A"}, {"target": "Ab", "value": 10, "source": "Bbm"}, {"source": "E", "value": 5, "target": "Bb"}, {"value": 8, "source": "E", "target": "Bbm"}, {"source": "Eb", "value": 10, "target": "Cm"}, {"value": 8, "target": "Fm", "source": "G/3"}, {"target": "G", "source": "D", "value": 5}, {"source": "C", "value": 8, "target": "Dm"}, {"target": "Bm", "source": "Am", "value": 10}, {"value": 8, "target": "Gb/5", "source": "Bb9"}, {"target": "Bm", "source": "Gb", "value": 8}, {"value": 8, "source": "G7", "target": "Bb"}, {"source": "Edim7", "target": "Dm", "value": 5}, {"source": "Db", "target": "A", "value": 15}, {"target": "Gb", "value": 10, "source": "Gb/5"}, {"target": "E", "value": 5, "source": "Gbm7b5"}, {"target": "C", "source": "B", "value": 12}, {"target": "Bbm", "value": 5, "source": "Adim7"}, {"value": 8, "target": "F", "source": "A"}, {"source": "Fm", "value": 10, "target": "Dbm"}, {"source": "G", "target": "Eb", "value": 12}, {"source": "Gb", "value": 8, "target": "C/3"}, {"target": "Bbm", "value": 10, "source": "Dm"}, {"target": "F", "source": "Abm", "value": 10}, {"source": "F", "value": 15, "target": "E"}, {"source": "Db", "target": "A", "value": 8}, {"target": "Ab/5", "value": 8, "source": "E7"}, {"value": 10, "target": "Bb", "source": "Gm"}, {"target": "Dbm", "source": "Bb", "value": 10}, {"source": "C", "value": 8, "target": "D"}, {"target": "Ab", "value": 5, "source": "Fm7b5"}, {"source": "G", "value": 8, "target": "Eb"}, {"source": "E", "value": 10, "target": "Am"}, {"source": "F", "target": "Db", "value": 15}, {"target": "Ab", "value": 10, "source": "A"}, {"value": 8, "source": "B", "target": "Cm"}, {"target": "Eb/3", "source": "Ab", "value": 8}, {"value": 8, "source": "Bb", "target": "C"}, {"source": "A7", "target": "F", "value": 8}, {"target": "Dbm", "source": "Ddim7", "value": 5}, {"target": "Db", "value": 5, "source": "Gbm7b5"}, {"target": "A", "source": "Bb", "value": 8}, {"source": "Abdim7", "target": "Am", "value": 5}, {"source": "Db", "target": "Eb", "value": 12}, {"target": "Ab/5", "value": 8, "source": "Bb9"}, {"target": "Bbm", "source": "Em", "value": 10}, {"source": "C/5", "target": "Eb", "value": 10}, {"target": "Dbm", "source": "Ebdim7", "value": 5}, {"target": "B", "source": "Abm7b5", "value": 5}, {"source": "D7", "value": 8, "target": "Bb/5"}, {"value": 8, "source": "D", "target": "Gb/3"}, {"target": "Bm", "source": "Ebm", "value": 10}, {"target": "A", "value": 5, "source": "Gbm7b5"}, {"source": "Dbm7b5", "target": "F", "value": 5}, {"value": 8, "source": "Bb9", "target": "C/5"}, {"source": "Em7b5", "target": "Gb", "value": 5}, {"source": "C", "value": 10, "target": "E"}, {"target": "A", "source": "B", "value": 12}, {"source": "Db", "target": "Em", "value": 10}, {"value": 8, "source": "G7", "target": "Db"}, {"source": "Bb", "value": 10, "target": "Bbm"}, {"target": "Gm", "value": 5, "source": "Adim7"}, {"source": "Fm", "target": "D", "value": 10}, {"target": "A", "source": "Abm7b5", "value": 5}, {"value": 8, "source": "G7", "target": "Eb"}, {"value": 8, "target": "C", "source": "Gm"}, {"source": "Fm7", "target": "C", "value": 8}, {"target": "Bm", "source": "Gdim7", "value": 5}, {"value": 8, "target": "Eb", "source": "Dbm7"}, {"source": "C", "target": "G", "value": 10}, {"source": "Bm7", "value": 8, "target": "A"}, {"target": "Bm", "value": 10, "source": "B"}, {"source": "G", "target": "Eb", "value": 10}, {"target": "Ab", "source": "E", "value": 10}, {"target": "G", "source": "Ab", "value": 10}, {"target": "Bm", "value": 8, "source": "A/3"}, {"source": "Abdim7", "value": 5, "target": "Bbm"}, {"value": 8, "source": "E", "target": "Fm"}, {"value": 8, "target": "Gb", "source": "Dbm7"}, {"value": 8, "target": "D/5", "source": "Bb9"}, {"value": 8, "source": "E", "target": "Am"}, {"source": "Db", "value": 15, "target": "Eb"}, {"source": "G", "value": 20, "target": "C"}, {"target": "Ab", "value": 8, "source": "Eb7"}, {"target": "Ebm", "value": 10, "source": "Abm"}, {"source": "Cm7b5", "value": 5, "target": "Bb"}, {"value": 8, "source": "E", "target": "Gb"}, {"source": "G", "target": "Em", "value": 10}, {"source": "Eb", "target": "Fm", "value": 8}, {"target": "Dbm", "source": "Abdim7", "value": 5}, {"value": 10, "source": "D", "target": "E"}, {"target": "A", "source": "Bm7b5", "value": 5}, {"source": "Db", "target": "D", "value": 10}, {"value": 8, "target": "Gb", "source": "Gm7"}, {"source": "F", "value": 8, "target": "C/3"}, {"value": 8, "target": "Dm", "source": "Eb/3"}, {"value": 8, "target": "Fm", "source": "Ab"}, {"value": 10, "target": "Am", "source": "Dm"}, {"source": "Bb", "target": "Db", "value": 5}, {"target": "Abm", "source": "Dbdim7", "value": 5}, {"source": "F", "target": "Eb", "value": 12}, {"target": "C", "value": 10, "source": "Gb/5"}, {"value": 10, "source": "Abm", "target": "Bb"}, {"value": 8, "source": "D", "target": "Cm"}, {"target": "Gbm", "source": "Bdim7", "value": 5}, {"target": "Abm", "value": 8, "source": "B"}, {"target": "G", "source": "D", "value": 10}, {"value": 5, "target": "Ebm", "source": "Adim7"}, {"source": "C", "target": "F", "value": 10}, {"value": 8, "source": "Gbm7b5", "target": "A/5"}, {"source": "Gdim7", "value": 5, "target": "Am"}, {"value": 8, "target": "Eb", "source": "Db7"}, {"value": 8, "source": "Ebm", "target": "Gb"}, {"source": "Gb", "value": 20, "target": "Bb"}, {"source": "Bm7b5", "value": 5, "target": "E"}, {"target": "G", "value": 5, "source": "Gbm7b5"}, {"source": "G", "target": "Gb", "value": 12}, {"value": 10, "target": "E", "source": "Gb/5"}, {"source": "Db", "value": 20, "target": "F"}, {"source": "Db", "target": "C", "value": 12}, {"target": "D", "source": "Dm7b5", "value": 5}, {"target": "A", "value": 8, "source": "Gm7"}, {"source": "Db", "target": "Gm", "value": 10}, {"target": "B", "source": "Bm7b5", "value": 5}, {"value": 10, "target": "Ebm", "source": "Gm"}, {"target": "F", "source": "Gm7b5", "value": 5}, {"target": "Ab", "source": "Abm7b5", "value": 5}, {"source": "C/5", "target": "G", "value": 10}, {"source": "E", "value": 5, "target": "E"}, {"value": 8, "source": "E", "target": "Bb"}, {"source": "F", "value": 10, "target": "Ebm"}, {"target": "D", "value": 10, "source": "Gm"}, {"source": "Dbdim7", "target": "Gbm", "value": 5}, {"source": "Cm7b5", "value": 5, "target": "E"}, {"source": "Db", "target": "A", "value": 20}, {"target": "F", "source": "D", "value": 10}, {"source": "G", "target": "Bm", "value": 8}, {"value": 10, "source": "A", "target": "Cm"}, {"target": "F", "source": "Bbm7b5", "value": 5}, {"target": "Ab", "value": 10, "source": "Dm"}, {"target": "Ab", "value": 10, "source": "Ab"}, {"source": "Ebdim7", "target": "Gm", "value": 5}, {"target": "Gb", "value": 5, "source": "Dm6"}, {"value": 8, "source": "Gb/3", "target": "Fm"}, {"target": "Ab/5", "value": 8, "source": "E9"}, {"target": "Bbm", "value": 10, "source": "Bbm"}, {"value": 10, "target": "Fm", "source": "Gm"}, {"value": 8, "source": "E9", "target": "C/5"}, {"source": "Bb", "target": "F", "value": 10}, {"value": 8, "target": "Fm", "source": "D/3"}, {"source": "Db", "target": "Bm", "value": 8}, {"source": "Db", "value": 8, "target": "Gm"}, {"source": "Ddim7", "target": "Gbm", "value": 5}, {"source": "Fm", "target": "B", "value": 10}, {"target": "A", "source": "Bb", "value": 10}, {"source": "F", "target": "Db", "value": 10}, {"target": "Em", "source": "Ebdim7", "value": 5}, {"source": "C", "value": 10, "target": "Ebm"}, {"value": 8, "target": "Dm", "source": "E/3"}, {"source": "Edim7", "target": "Fm", "value": 5}, {"value": 8, "source": "Bb", "target": "E"}, {"target": "Abm", "source": "Dbm", "value": 10}, {"source": "Ab7", "target": "E/5", "value": 8}, {"value": 8, "source": "D", "target": "E"}, {"value": 8, "target": "C", "source": "Db7"}, {"value": 8, "target": "Gm", "source": "D"}, {"target": "B", "value": 10, "source": "Dm"}, {"target": "Dbm", "value": 10, "source": "Gm"}, {"target": "D", "source": "A7", "value": 8}, {"value": 8, "source": "A", "target": "Gb/3"}, {"value": 8, "target": "G", "source": "D"}, {"value": 10, "target": "C/5", "source": "Bbm"}, {"source": "G", "target": "Gb", "value": 10}, {"target": "Eb/5", "value": 10, "source": "Dm"}, {"target": "Em", "value": 8, "source": "B"}, {"source": "Bb", "target": "Gb", "value": 10}, {"source": "Eb", "target": "G", "value": 10}, {"source": "Fm7", "value": 8, "target": "A"}, {"source": "Em7b5", "target": "F", "value": 5}, {"source": "Bm7", "target": "C", "value": 8}, {"value": 8, "target": "E", "source": "Db7"}, {"source": "Fm", "target": "Gm", "value": 10}, {"target": "Db", "value": 10, "source": "B"}, {"source": "F", "value": 8, "target": "Dm"}, {"source": "F", "value": 15, "target": "G"}, {"target": "B", "value": 5, "source": "Fm7b5"}, {"source": "Bbm7b5", "value": 5, "target": "Eb"}, {"source": "Em", "target": "Am", "value": 10}, {"target": "F/5", "source": "Bbm7b5", "value": 8}, {"target": "Dm", "source": "Bbdim7", "value": 5}, {"target": "Abm", "source": "F/3", "value": 8}, {"source": "Dm7b5", "target": "F", "value": 5}, {"source": "Fm", "target": "Eb/5", "value": 10}, {"target": "A", "source": "Gm7b5", "value": 5}, {"source": "C", "value": 10, "target": "Ab"}, {"value": 10, "target": "Ebm", "source": "Bbm"}, {"target": "Eb/5", "source": "Ebm", "value": 10}, {"source": "Dbdim7", "target": "Dm", "value": 5}, {"target": "Ab/5", "value": 8, "source": "Bbm7b5"}, {"target": "A", "source": "E", "value": 8}, {"source": "Bb", "target": "Gbm", "value": 10}, {"value": 8, "target": "Dm", "source": "G/3"}, {"source": "Dbdim7", "value": 5, "target": "Cm"}, {"value": 8, "target": "D/5", "source": "E9"}, {"value": 8, "source": "C9", "target": "Bb/5"}, {"value": 10, "target": "Gbm", "source": "B"}, {"value": 8, "target": "F", "source": "Eb7"}, {"source": "Bm", "target": "Am", "value": 10}, {"target": "Bm", "source": "Bm", "value": 10}, {"target": "Dbm", "value": 5, "source": "Adim7"}, {"source": "C/5", "target": "Db", "value": 10}, {"source": "Gb", "value": 8, "target": "Gb/3"}, {"target": "Bm", "value": 8, "source": "E/3"}, {"source": "G", "value": 8, "target": "Ebm"}, {"source": "Em", "target": "Ebm", "value": 10}, {"target": "D", "source": "Eb", "value": 10}, {"target": "B", "value": 10, "source": "B"}, {"source": "Cm7b5", "target": "G", "value": 5}, {"source": "Bb", "target": "G", "value": 5}, {"source": "G", "value": 10, "target": "Dbm"}, {"target": "Bm", "value": 10, "source": "Gm"}, {"source": "Am", "target": "Abm", "value": 10}, {"value": 5, "source": "Ab", "target": "Bb"}, {"target": "D", "source": "Abm7b5", "value": 5}, {"value": 10, "source": "Ab", "target": "Bb"}]