[{"target": "E/64", "source": "Em6", "value": 5}, {"target": "Dm", "source": "Cm", "value": 10}, {"target": "Gb", "source": "E", "value": 8}, {"target": "Gb", "value": 8, "source": "Dbm"}, {"target": "Eb", "source": "Db", "value": 15}, {"target": "C", "value": 8, "source": "G"}, {"value": 5, "target": "G", "source": "Dm7b5/64"}, {"value": 8, "target": "Ab", "source": "A7"}, {"target": "Cm", "source": "Gm", "value": 10}, {"source": "Bb7", "value": 8, "target": "D/6"}, {"value": 10, "target": "Gb", "source": "Fm"}, {"value": 5, "target": "G", "source": "F"}, {"target": "B", "value": 5, "source": "Gbm7b5/64"}, {"source": "Adim7", "target": "Bbm", "value": 5}, {"target": "C", "source": "Bb", "value": 8}, {"target": "Eb", "value": 8, "source": "Bbm"}, {"target": "Cm", "source": "Bdim7", "value": 5}, {"target": "Db", "value": 12, "source": "Gb"}, {"value": 8, "target": "G/64", "source": "C"}, {"target": "Abm", "source": "Gdim7", "value": 5}, {"source": "A/6", "value": 8, "target": "Bm"}, {"value": 10, "source": "Cm", "target": "Bb/64"}, {"source": "Ebdim7", "target": "Em", "value": 5}, {"source": "A", "value": 8, "target": "D/64"}, {"value": 8, "source": "Eb", "target": "F"}, {"value": 20, "target": "Bb", "source": "F"}, {"target": "D", "source": "Am", "value": 10}, {"value": 8, "target": "Fm", "source": "Eb/6"}, {"target": "Gb", "source": "Db", "value": 8}, {"source": "Bm", "target": "Dbm", "value": 10}, {"source": "Abdim7", "target": "Am", "value": 5}, {"source": "Db", "value": 8, "target": "Gbm"}, {"source": "A", "value": 8, "target": "D"}, {"value": 8, "target": "Eb/6", "source": "B7"}, {"value": 8, "target": "B/6", "source": "G7"}, {"value": 8, "target": "A", "source": "G"}, {"target": "F", "value": 20, "source": "C"}, {"target": "Gm", "source": "Dm", "value": 10}, {"target": "Db", "source": "B", "value": 8}, {"value": 8, "source": "F7", "target": "E"}, {"source": "Db", "target": "Bbm", "value": 10}, {"target": "Fm", "source": "Edim7", "value": 5}, {"target": "Am", "source": "C", "value": 10}, {"target": "Gb", "source": "E", "value": 15}, {"value": 10, "source": "D/64", "target": "A"}, {"source": "Gb/64", "target": "Ab", "value": 5}, {"target": "D/64", "value": 10, "source": "Em"}, {"value": 10, "source": "Abm", "target": "Gb/64"}, {"target": "Bb", "value": 10, "source": "F"}, {"source": "Ebm", "value": 10, "target": "Db/64"}, {"source": "Dm7b5", "value": 8, "target": "Ab/64"}, {"source": "Am7b5", "target": "D", "value": 5}, {"source": "C7", "value": 8, "target": "E/6"}, {"value": 8, "source": "Db/6", "target": "Ebm"}, {"target": "Gb", "source": "Bm7", "value": 8}, {"source": "Am6", "target": "B", "value": 5}, {"value": 8, "target": "D", "source": "G/64"}, {"value": 10, "target": "Gbm", "source": "Em"}, {"target": "G", "source": "C", "value": 10}, {"value": 5, "target": "A", "source": "G/64"}, {"target": "C", "value": 8, "source": "Fm7"}, {"target": "B", "source": "Gbm7b5", "value": 5}, {"value": 8, "source": "Gb", "target": "Bm"}, {"value": 8, "target": "F", "source": "C"}, {"source": "Gbm", "target": "Abm", "value": 10}, {"target": "Db", "value": 5, "source": "Abm7b5/64"}, {"value": 10, "target": "C", "source": "F/64"}, {"source": "Gb", "target": "Ab", "value": 5}, {"source": "Bm", "target": "Em", "value": 10}, {"value": 8, "target": "Bbm", "source": "F"}, {"target": "Db/6", "value": 8, "source": "A7"}, {"source": "Ebm6", "target": "F", "value": 5}, {"value": 12, "target": "Gb", "source": "B"}, {"target": "Dm", "value": 8, "source": "C/6"}, {"value": 5, "target": "A", "source": "Em7b5"}, {"source": "Bb7", "value": 8, "target": "A"}, {"target": "B", "value": 12, "source": "E"}, {"value": 8, "target": "Bb/64", "source": "Em7b5"}, {"target": "C", "source": "Gm7b5", "value": 5}, {"value": 20, "source": "Eb", "target": "Ab"}, {"source": "Gbm", "value": 10, "target": "E/64"}, {"source": "Bb", "target": "F", "value": 10}, {"value": 10, "target": "Bbm", "source": "Ab"}, {"source": "Eb", "value": 10, "target": "Bb"}, {"source": "Gbm7b5", "target": "G", "value": 5}, {"value": 15, "target": "D", "source": "C"}, {"target": "C", "value": 20, "source": "G"}, {"source": "A/64", "value": 10, "target": "E"}, {"source": "Ebm", "value": 10, "target": "E"}, {"source": "Abm", "target": "Bbm", "value": 10}, {"target": "Db/64", "value": 8, "source": "Ab"}, {"source": "A", "target": "B", "value": 5}, {"target": "Eb", "source": "Bbm7b5/64", "value": 5}, {"value": 5, "source": "D", "target": "E"}, {"target": "Dm", "source": "Dbdim7", "value": 5}, {"source": "Gbm6", "target": "Ab", "value": 5}, {"value": 10, "target": "Fm", "source": "Ab"}, {"target": "Gb", "source": "Dbm7b5", "value": 5}, {"value": 8, "target": "A/64", "source": "D"}, {"source": "Am6", "target": "A/64", "value": 5}, {"value": 8, "source": "B7", "target": "Bb"}, {"value": 12, "target": "C", "source": "F"}, {"target": "Db/64", "source": "Dbm6", "value": 5}, {"value": 8, "source": "Ab/6", "target": "Bbm"}, {"value": 8, "target": "D/64", "source": "Abm7b5"}, {"source": "B", "value": 8, "target": "E"}, {"source": "Bb/64", "value": 8, "target": "F"}, {"source": "Dm6", "target": "D/64", "value": 5}, {"value": 8, "target": "D", "source": "C"}, {"source": "Bm", "value": 8, "target": "E"}, {"target": "B", "source": "E", "value": 10}, {"target": "Gm", "value": 10, "source": "F"}, {"target": "C", "value": 10, "source": "F"}, {"source": "Gbm", "value": 8, "target": "B"}, {"value": 12, "source": "Eb", "target": "Bb"}, {"source": "Ebm", "target": "Ab", "value": 10}, {"target": "Db/64", "value": 8, "source": "Gb"}, {"target": "D", "source": "Cm6", "value": 5}, {"value": 5, "target": "G", "source": "Fm6"}, {"target": "Eb", "source": "Dbm6", "value": 5}, {"target": "Eb", "source": "Dm", "value": 10}, {"source": "Gb7", "value": 8, "target": "Bb/6"}, {"target": "Eb", "source": "Bb", "value": 20}, {"target": "E/64", "source": "B", "value": 8}, {"source": "Cm", "target": "Fm", "value": 10}, {"target": "B/64", "source": "Bm6", "value": 5}, {"target": "B", "source": "Bbm7b5", "value": 5}, {"source": "Dm", "target": "Em", "value": 10}, {"source": "E", "value": 8, "target": "A/64"}, {"value": 8, "target": "F", "source": "Bbm7"}, {"value": 8, "target": "G", "source": "C/64"}, {"source": "Cm7b5/64", "target": "F", "value": 5}, {"target": "D", "value": 10, "source": "G"}, {"target": "Db", "value": 20, "source": "Ab"}, {"source": "Db/64", "value": 8, "target": "Ab"}, {"value": 12, "source": "Bb", "target": "F"}, {"value": 10, "source": "Eb/64", "target": "Bb"}, {"target": "Eb", "source": "Bb", "value": 10}, {"value": 8, "target": "Eb/64", "source": "Ab"}, {"source": "Gb", "target": "Ab", "value": 15}, {"source": "Ab9", "value": 8, "target": "Bb/64"}, {"target": "Am", "source": "Gm", "value": 10}, {"target": "Gb", "source": "B", "value": 10}, {"target": "C", "source": "Bm7b5", "value": 5}, {"target": "Gm", "value": 8, "source": "D"}, {"value": 8, "source": "Eb7", "target": "D"}, {"target": "Db", "source": "Cm", "value": 10}, {"target": "Dbm", "source": "Abm", "value": 10}, {"target": "C", "value": 10, "source": "G"}, {"target": "F", "value": 10, "source": "Em"}, {"source": "Bm", "target": "C", "value": 10}, {"value": 5, "source": "Fm7b5", "target": "Bb"}, {"source": "A", "value": 10, "target": "Bm"}, {"value": 8, "source": "Eb", "target": "Ab"}, {"value": 5, "source": "Bm7b5/64", "target": "E"}, {"value": 8, "target": "F/64", "source": "C"}, {"source": "Bb", "value": 10, "target": "Gm"}, {"target": "Gb", "source": "Dbm7b5/64", "value": 5}, {"target": "Gm", "value": 8, "source": "F/6"}, {"target": "Ab/64", "value": 10, "source": "Bbm"}, {"source": "A", "value": 12, "target": "E"}, {"target": "B", "source": "E/64", "value": 10}, {"source": "B/6", "value": 8, "target": "Dbm"}, {"source": "Ebm7b5/64", "target": "Ab", "value": 5}, {"value": 10, "source": "E", "target": "Gbm"}, {"value": 5, "source": "Fm7b5/64", "target": "Bb"}, {"source": "Adim/6", "target": "Bm", "value": 5}, {"target": "C", "source": "Bb", "value": 15}, {"source": "A/64", "value": 8, "target": "E"}, {"target": "Cm", "value": 10, "source": "Bbm"}, {"target": "Db/64", "value": 8, "source": "Gm7b5"}, {"value": 8, "target": "Fm", "source": "C"}, {"value": 10, "source": "D", "target": "A"}, {"value": 15, "source": "Ab", "target": "Bb"}, {"value": 8, "target": "B/64", "source": "Gb"}, {"target": "Am", "value": 10, "source": "Em"}, {"source": "Ddim/6", "target": "Em", "value": 5}, {"source": "Ab7", "value": 8, "target": "G"}, {"target": "D", "value": 10, "source": "G/64"}, {"target": "Gb", "source": "E/64", "value": 5}, {"value": 8, "source": "Dm", "target": "G"}, {"source": "A", "value": 10, "target": "E"}, {"value": 8, "target": "G", "source": "Cm7"}, {"target": "F", "source": "C", "value": 10}, {"value": 8, "source": "G9", "target": "A/64"}, {"source": "A/64", "target": "B", "value": 5}, {"target": "B", "source": "C7", "value": 8}, {"target": "C", "value": 8, "source": "F/64"}, {"source": "Cm", "target": "F", "value": 10}, {"source": "Ab7", "target": "C/6", "value": 8}, {"value": 8, "target": "Gb/64", "source": "Cm7b5"}, {"value": 10, "source": "Am", "target": "Bm"}, {"target": "Db", "value": 5, "source": "Cm7b5"}, {"value": 5, "source": "Dm6", "target": "E"}, {"target": "B/64", "value": 8, "source": "A9"}, {"value": 12, "target": "D", "source": "G"}, {"target": "Db", "value": 8, "source": "Ab"}, {"target": "B", "source": "Gb", "value": 10}, {"value": 8, "target": "G/64", "source": "D"}, {"source": "Dbm7b5", "target": "D", "value": 5}, {"value": 10, "source": "E", "target": "A"}, {"value": 8, "source": "C9", "target": "D/64"}, {"source": "Ebm", "target": "Fm", "value": 10}, {"value": 8, "source": "E9", "target": "Gb/64"}, {"value": 10, "target": "Ebm", "source": "Bbm"}, {"target": "Ab/64", "value": 5, "source": "Abm6"}, {"value": 5, "source": "Am7b5", "target": "Bb"}, {"source": "Bbdim7", "target": "Bm", "value": 5}, {"source": "Am", "value": 10, "target": "Bb"}, {"source": "Gm", "target": "Ab", "value": 10}, {"value": 10, "target": "Eb/64", "source": "Fm"}, {"target": "Eb", "source": "Ab/64", "value": 8}, {"target": "C", "source": "Bb", "value": 5}, {"value": 8, "target": "G", "source": "D"}, {"target": "Cm", "source": "Bb", "value": 10}, {"source": "A", "value": 8, "target": "E/64"}, {"target": "F", "source": "Eb/64", "value": 5}, {"target": "D", "source": "C", "value": 5}, {"source": "Gb7", "value": 8, "target": "F"}, {"value": 5, "target": "F", "source": "Cm7b5"}, {"target": "Db", "source": "B", "value": 15}, {"target": "B/64", "source": "Dbm", "value": 10}, {"target": "G", "source": "F/64", "value": 5}, {"value": 10, "target": "A", "source": "Em"}, {"value": 8, "target": "Ab", "source": "Dbm7"}, {"target": "Eb", "value": 10, "source": "Bbm"}, {"value": 5, "source": "Bm7b5", "target": "E"}, {"source": "Bbm6", "target": "Bb/64", "value": 5}, {"source": "Db7", "target": "F/6", "value": 8}, {"value": 5, "source": "Abm7b5", "target": "A"}, {"source": "A", "value": 20, "target": "D"}, {"value": 8, "source": "Eb", "target": "Bb/64"}, {"source": "E/6", "value": 8, "target": "Gbm"}, {"source": "Bb", "value": 8, "target": "Ebm"}, {"target": "Db", "value": 8, "source": "Abm"}, {"target": "Eb", "source": "Db", "value": 5}, {"target": "Gb/6", "value": 8, "source": "D7"}, {"value": 5, "target": "A", "source": "G"}, {"value": 15, "target": "G", "source": "F"}, {"value": 8, "target": "G", "source": "F"}, {"source": "Em7b5/64", "target": "A", "value": 5}, {"value": 15, "source": "Eb", "target": "F"}, {"source": "Gb/64", "value": 10, "target": "Db"}, {"target": "D", "source": "Dbm", "value": 10}, {"target": "Eb", "source": "Db/64", "value": 5}, {"source": "Gm6", "target": "G/64", "value": 5}, {"target": "Gb", "source": "Em6", "value": 5}, {"value": 10, "source": "Dbm", "target": "Gbm"}, {"source": "Eb", "target": "F", "value": 5}, {"value": 5, "source": "Ab/64", "target": "Bb"}, {"value": 8, "source": "Am7b5", "target": "Eb/64"}, {"target": "G/64", "source": "Am", "value": 10}, {"source": "Dbdim/6", "target": "Ebm", "value": 5}, {"target": "Eb", "value": 8, "source": "Abm7"}, {"target": "Eb", "source": "Bb", "value": 8}, {"value": 8, "source": "Eb/64", "target": "Bb"}, {"source": "Bm", "value": 10, "target": "A/64"}, {"target": "Eb", "source": "Ab/64", "value": 10}, {"source": "Gbm", "value": 10, "target": "Bm"}, {"value": 8, "target": "C/64", "source": "G"}, {"target": "Ab/64", "value": 8, "source": "Gb9"}, {"source": "Dm", "target": "G", "value": 10}, {"source": "Em7", "value": 8, "target": "B"}, {"target": "Db", "value": 8, "source": "Gbm7"}, {"target": "F/64", "value": 8, "source": "Bm7b5"}, {"value": 5, "target": "Bbm", "source": "Abdim/6"}, {"target": "Gb", "source": "B/64", "value": 10}, {"target": "Db/64", "value": 8, "source": "B9"}, {"target": "B/64", "source": "E", "value": 8}, {"value": 8, "source": "E", "target": "Am"}, {"target": "Gm", "source": "Fdim/6", "value": 5}, {"target": "Gb", "value": 8, "source": "G7"}, {"source": "B", "value": 8, "target": "Em"}, {"source": "Db7", "target": "C", "value": 8}, {"source": "Db", "value": 8, "target": "Gb/64"}, {"target": "Dm", "source": "C", "value": 10}, {"value": 10, "target": "Bbm", "source": "Fm"}, {"source": "Gm7b5", "target": "Ab", "value": 5}, {"value": 8, "target": "D", "source": "Am"}, {"value": 8, "source": "Am7", "target": "E"}, {"target": "Gb", "source": "Db", "value": 10}, {"target": "Am", "value": 10, "source": "G"}, {"value": 20, "target": "G", "source": "D"}, {"value": 8, "target": "C/64", "source": "Bb9"}, {"source": "Gbm", "target": "G", "value": 10}, {"target": "Gb", "source": "E", "value": 5}, {"source": "B", "value": 20, "target": "E"}, {"target": "G", "value": 10, "source": "C/64"}, {"value": 8, "source": "F9", "target": "G/64"}, {"target": "Dm", "source": "Am", "value": 10}, {"source": "Bb", "value": 8, "target": "Eb/64"}, {"target": "B", "source": "Gb", "value": 20}, {"value": 8, "source": "Fm", "target": "Bb"}, {"target": "Db", "source": "Bm6", "value": 5}, {"target": "D", "source": "Am7b5/64", "value": 5}, {"value": 10, "source": "Fm", "target": "Bb"}, {"target": "Dm", "value": 10, "source": "F"}, {"target": "C", "source": "Bbm6", "value": 5}, {"value": 5, "target": "F", "source": "Em7b5"}, {"target": "Abm", "source": "B", "value": 10}, {"target": "Ab/64", "value": 8, "source": "Eb"}, {"target": "E/64", "value": 8, "source": "Bbm7b5"}, {"value": 8, "source": "Ab", "target": "Bb"}, {"source": "Bm", "value": 10, "target": "E"}, {"value": 5, "target": "F/64", "source": "Fm6"}, {"source": "B", "value": 10, "target": "E"}, {"target": "E/64", "value": 8, "source": "D9"}, {"value": 10, "target": "Bm", "source": "D"}, {"source": "Ddim7", "target": "Ebm", "value": 5}, {"source": "Gbm", "target": "B", "value": 10}, {"value": 8, "source": "D", "target": "E"}, {"value": 8, "source": "Cm", "target": "F"}, {"target": "Dm", "source": "Cdim/6", "value": 5}, {"value": 10, "source": "Dbm", "target": "Ebm"}, {"target": "Abm", "source": "Gb", "value": 10}, {"source": "Bb/64", "target": "C", "value": 5}, {"source": "B", "target": "Dbm", "value": 10}, {"target": "Eb/64", "source": "Ebm6", "value": 5}, {"source": "A", "value": 10, "target": "Gbm"}, {"value": 10, "source": "Abm", "target": "A"}, {"source": "A", "target": "B", "value": 15}, {"value": 8, "target": "Bb/64", "source": "F"}, {"source": "Gb/64", "value": 8, "target": "Db"}, {"target": "B/64", "value": 8, "source": "Fm7b5"}, {"source": "Edim/6", "target": "Gbm", "value": 5}, {"source": "Gbm6", "target": "Gb/64", "value": 5}, {"target": "A/6", "value": 8, "source": "F7"}, {"source": "Gm7b5/64", "target": "C", "value": 5}, {"source": "Bb", "value": 8, "target": "F/64"}, {"target": "B", "value": 10, "source": "Bbm"}, {"source": "E", "value": 20, "target": "A"}, {"target": "Db", "source": "B/64", "value": 5}, {"value": 8, "source": "Gb", "target": "Ab"}, {"source": "Ebm", "target": "Abm", "value": 10}, {"value": 12, "target": "Eb", "source": "Ab"}, {"target": "Dbm", "source": "Cdim7", "value": 5}, {"value": 8, "source": "D/64", "target": "A"}, {"value": 5, "target": "Cm", "source": "Bbdim/6"}, {"target": "Gb", "source": "Dbm", "value": 10}, {"value": 5, "source": "Ab", "target": "Bb"}, {"source": "Gbdim7", "target": "Gm", "value": 5}, {"target": "Db", "source": "Abm7b5", "value": 5}, {"value": 8, "target": "A", "source": "Em"}, {"source": "E", "target": "Dbm", "value": 10}, {"value": 10, "target": "Em", "source": "D"}, {"value": 8, "target": "F/64", "source": "Eb9"}, {"target": "Cm", "value": 8, "source": "Bb/6"}, {"target": "Dbm", "source": "Bdim/6", "value": 5}, {"value": 15, "target": "A", "source": "G"}, {"target": "Db", "value": 8, "source": "D7"}, {"value": 10, "target": "Gm", "source": "Fm"}, {"value": 12, "target": "G", "source": "C"}, {"value": 10, "source": "Db", "target": "Ebm"}, {"source": "Eb", "target": "Ab", "value": 10}, {"target": "Eb", "source": "Bbm7b5", "value": 5}, {"source": "E7", "target": "Eb", "value": 8}, {"value": 8, "target": "D", "source": "Gm7"}, {"source": "A", "value": 8, "target": "B"}, {"target": "B", "source": "E/64", "value": 8}, {"source": "Ebm", "value": 8, "target": "Ab"}, {"source": "Gm6", "target": "A", "value": 5}, {"target": "Db", "source": "Abm", "value": 10}, {"value": 8, "target": "D/64", "source": "G"}, {"target": "B", "value": 8, "source": "Gb"}, {"source": "Dm", "target": "C/64", "value": 10}, {"target": "Gb", "source": "Fm7b5", "value": 5}, {"source": "Dm7b5", "target": "Eb", "value": 5}, {"source": "Ebm7", "value": 8, "target": "Bb"}, {"target": "F/64", "source": "Gm", "value": 10}, {"source": "A", "target": "D", "value": 10}, {"value": 15, "source": "D", "target": "E"}, {"source": "Db", "target": "Ab", "value": 10}, {"target": "Abm", "value": 8, "source": "Gb/6"}, {"target": "Abm", "value": 8, "source": "Eb"}, {"target": "Eb", "source": "Db", "value": 8}, {"value": 8, "target": "Bb", "source": "F"}, {"target": "Gb", "source": "Db", "value": 20}, {"value": 8, "source": "Ebm7b5", "target": "A/64"}, {"source": "A", "target": "Dm", "value": 8}, {"source": "Db/64", "target": "Ab", "value": 10}, {"source": "Dbm7b5", "value": 8, "target": "G/64"}, {"value": 5, "target": "Bb", "source": "Abm6"}, {"value": 5, "target": "Fm", "source": "Ebdim/6"}, {"value": 8, "target": "C/64", "source": "F"}, {"target": "Cm", "value": 8, "source": "G"}, {"value": 5, "source": "Ebm7b5", "target": "E"}, {"target": "Em", "value": 10, "source": "G"}, {"value": 8, "source": "Eb7", "target": "G/6"}, {"source": "Ebm7b5", "target": "Ab", "value": 5}, {"source": "D/6", "value": 8, "target": "Em"}, {"target": "Am", "source": "Gdim/6", "value": 5}, {"value": 8, "target": "Gb", "source": "B/64"}, {"source": "Bb/64", "target": "F", "value": 10}, {"value": 8, "target": "Dbm", "source": "Ab"}, {"value": 8, "target": "Am", "source": "G/6"}, {"source": "Db9", "value": 8, "target": "Eb/64"}, {"value": 5, "target": "D", "source": "C/64"}, {"value": 12, "source": "Db", "target": "Ab"}, {"source": "Eb", "target": "Fm", "value": 10}, {"target": "C", "source": "Gm", "value": 10}, {"source": "E7", "target": "Ab/6", "value": 8}, {"value": 10, "source": "Gb", "target": "Ebm"}, {"source": "E", "value": 8, "target": "A"}, {"target": "C", "value": 8, "source": "Gm"}, {"target": "Db", "value": 10, "source": "Ab"}, {"value": 10, "target": "Eb", "source": "Ab"}, {"target": "Cm", "source": "Eb", "value": 10}, {"target": "Db", "source": "Gb", "value": 10}, {"target": "Abm", "source": "Gbdim/6", "value": 5}, {"target": "C/64", "source": "Cm6", "value": 5}, {"value": 5, "source": "D/64", "target": "E"}, {"source": "Fdim7", "target": "Gbm", "value": 5}, {"source": "B", "value": 8, "target": "Gb/64"}, {"source": "Dm7b5", "target": "G", "value": 5}, {"target": "Db", "source": "B", "value": 5}, {"value": 10, "target": "G", "source": "D"}, {"value": 8, "source": "Gbm7b5", "target": "C/64"}, {"value": 8, "target": "A", "source": "Dm7"}, {"target": "Ab/64", "source": "Db", "value": 8}, {"value": 12, "source": "D", "target": "A"}]